chlore/__init__.py
chlore/_pytest_plugin.py
chlore/app.py
chlore/config.py
chlore/controller.py
chlore/database.py
chlore/errors.py
chlore/etna_auth.py
chlore/form.py
chlore/jinja.py
chlore/logging.py
chlore/messages.py
chlore/rabbitmq.py
chlore/request.py
chlore/test_config.py
chlore/test_etna_auth.py
chlore/testing/__init__.py
chlore/testing/dependencies.py
chlore/testing/web.py
chlore-0.14.6.dist-info/LICENSE
chlore-0.14.6.dist-info/METADATA
chlore-0.14.6.dist-info/WHEEL
chlore-0.14.6.dist-info/entry_points.txt
chlore-0.14.6.dist-info/RECORD
